{"mean":{"confidence_interval":{"confidence_level":0.95,"lower_bound":17567.29204304166,"upper_bound":17587.8133020316},"point_estimate":17576.866162204187,"standard_error":5.244224436533805},"median":{"confidence_interval":{"confidence_level":0.95,"lower_bound":17554.357852462483,"upper_bound":17564.12636664124},"point_estimate":17557.103626713844,"standard_error":2.458783135606341},"median_abs_dev":{"confidence_interval":{"confidence_level":0.95,"lower_bound":14.374857710657029,"upper_bound":26.36671640953777},"point_estimate":18.53900230244577,"standard_error":2.9753511961854815},"slope":{"confidence_interval":{"confidence_level":0.95,"lower_bound":17571.253420403933,"upper_bound":17597.545485325958},"point_estimate":17584.32981719853,"standard_error":6.715911381141722},"std_dev":{"confidence_interval":{"confidence_level":0.95,"lower_bound":35.57129890901732,"upper_bound":68.69023205218505},"point_estimate":52.74883986715671,"standard_error":8.503076943795747}}